CHANGES.txt
README.txt
bootstrap.py
buildout.cfg
setup.cfg
setup.py
textindexng/__init__.py
zopyx/__init__.py
zopyx.txng3.core.egg-info/PKG-INFO
zopyx.txng3.core.egg-info/SOURCES.txt
zopyx.txng3.core.egg-info/dependency_links.txt
zopyx.txng3.core.egg-info/namespace_packages.txt
zopyx.txng3.core.egg-info/requires.txt
zopyx.txng3.core.egg-info/top_level.txt
zopyx/txng3/__init__.py
zopyx/txng3/core/LICENSE.txt
zopyx/txng3/core/ZPL.txt
zopyx/txng3/core/__init__.py
zopyx/txng3/core/baseconverter.py
zopyx/txng3/core/compatible.py
zopyx/txng3/core/config.py
zopyx/txng3/core/configure.zcml
zopyx/txng3/core/content.py
zopyx/txng3/core/docidlist.py
zopyx/txng3/core/evaluator.py
zopyx/txng3/core/exceptions.py
zopyx/txng3/core/grokindex.py
zopyx/txng3/core/index.py
zopyx/txng3/core/lexicon.py
zopyx/txng3/core/logger.py
zopyx/txng3/core/nbest.py
zopyx/txng3/core/normalization.py
zopyx/txng3/core/parsetree.py
zopyx/txng3/core/ranking.py
zopyx/txng3/core/resultset.py
zopyx/txng3/core/searchrequest.py
zopyx/txng3/core/shell.py
zopyx/txng3/core/splitter.py
zopyx/txng3/core/stemmer.py
zopyx/txng3/core/stopwords.py
zopyx/txng3/core/storage.py
zopyx/txng3/core/thesaurus.py
zopyx/txng3/core/util.py
zopyx/txng3/core/vocabulary.py
zopyx/txng3/core/widcode.py
zopyx/txng3/core/wordlist.py
zopyx/txng3/core/converters/StripTagParser.py
zopyx/txng3/core/converters/__init__.py
zopyx/txng3/core/converters/configure.zcml
zopyx/txng3/core/converters/doc.py
zopyx/txng3/core/converters/entities.py
zopyx/txng3/core/converters/entities2uc.py
zopyx/txng3/core/converters/html.py
zopyx/txng3/core/converters/null.py
zopyx/txng3/core/converters/ooffice.py
zopyx/txng3/core/converters/pdf.py
zopyx/txng3/core/converters/ppt.py
zopyx/txng3/core/converters/ps.py
zopyx/txng3/core/converters/rtf.py
zopyx/txng3/core/converters/sgml.py
zopyx/txng3/core/converters/wvText.xml
zopyx/txng3/core/converters/xls.py
zopyx/txng3/core/converters/stripogram/HTMLParser.py
zopyx/txng3/core/converters/stripogram/__init__.py
zopyx/txng3/core/converters/stripogram/html2safehtml.py
zopyx/txng3/core/converters/stripogram/html2text.py
zopyx/txng3/core/converters/stripogram/license.txt
zopyx/txng3/core/converters/stripogram/readme.txt
