Metadata-Version: 1.0
Name: zopyx.txng3.core
Version: 3.5.3
Summary: TextIndexNG3 core implementation
Home-page: http://sf.net/projects/textindexng/
Author: Andreas Jung, ZOPYX Ltd. & Co. KG
Author-email: info@zopyx.com
License: UNKNOWN
Platform: UNKNOWN
